{
  "publicPath": "/_nuxt/",
  "all": [
    "../server/index.spa.html",
    "../server/index.ssr.html",
    "0091f0b.js",
    "0521cd7.js",
    "0655349.js",
    "08c86a0.js",
    "09eb257.js",
    "0ab9730.js",
    "0dccafc.js",
    "0e52890.js",
    "102ffbc.js",
    "11651d5.js",
    "11a7210.js",
    "126a84d.js",
    "14e9e8d.js",
    "1879fdc.js",
    "1c9f7ce.js",
    "1d35849.js",
    "1d676ef.js",
    "20f0c0a.js",
    "20fcf78.js",
    "26e0e1c.js",
    "28fb761.js",
    "2e83be0.js",
    "2e90e47.js",
    "2f875ce.js",
    "32780cc.js",
    "338d535.js",
    "33d0554.js",
    "372b076.js",
    "37bd4c7.js",
    "3867d75.js",
    "39b8c1c.js",
    "3d8a986.js",
    "3f95d30.js",
    "4106bfa.js",
    "42720ec.js",
    "4442a57.js",
    "44786c9.js",
    "458b9f1.js",
    "4b1e8a3.js",
    "4c30673.js",
    "4d79287.js",
    "4e9fdbc.js",
    "54d54e1.js",
    "57b46cd.js",
    "5b02a74.js",
    "5ca6e04.js",
    "5debb3b.js",
    "5f15256.js",
    "5ff4294.js",
    "6456d68.js",
    "64b37f0.js",
    "66ee803.js",
    "6b6657d.js",
    "6c22cff.js",
    "6e8eb97.js",
    "7039dd4.js",
    "7132b24.js",
    "748dbac.js",
    "7557e2f.js",
    "75c7c22.js",
    "7b54047.js",
    "7f5a696.js",
    "822fb99.js",
    "8303e45.js",
    "837a01e.js",
    "864d5e0.js",
    "87ea06f.js",
    "8bc2018.js",
    "8cec888.js",
    "927b8f7.js",
    "946a562.js",
    "97f557a.js",
    "99a3003.js",
    "9b309b2.js",
    "9e92977.js",
    "LICENSES",
    "a0fa3ac.js",
    "a21c123.js",
    "a6cb12b.js",
    "a777ec7.js",
    "b0e4ff8.js",
    "b404adc.js",
    "b512243.js",
    "b796d96.js",
    "b88c4ab.js",
    "bb2272a.js",
    "bcd9d9a.js",
    "bd13174.js",
    "bd417ce.js",
    "be25047.js",
    "c45aa79.js",
    "c88a534.js",
    "cd1d049.js",
    "cd40c37.js",
    "d26d2f8.js",
    "d9a21fe.js",
    "dd13d0a.js",
    "de07aa1.js",
    "de25305.js",
    "decbd27.js",
    "df9264f.js",
    "dfad095.js",
    "e04c5ef.js",
    "e23cb26.js",
    "e47888f.js",
    "e8825c2.js",
    "ec237bc.js",
    "edff888.js",
    "f106e75.js",
    "f19ab22.js",
    "f49c04d.js",
    "f4d1f31.js",
    "fbb668d.js",
    "fdfbde4.js",
    "fonts/NotoSansLao-Light.1de047f.ttf",
    "fonts/NotoSansLaoUI-Regular.29e0b55.ttf",
    "fonts/Roboto-Regular.a8d6ac0.ttf",
    "img/BWLOGO.9caee6e.jpeg",
    "img/cash.b97ff15.svg",
    "img/cashier.a8bb445.svg",
    "img/cashier_2.208aede.svg",
    "img/company_logo.01515f7.jpeg",
    "img/invoice.45f420f.svg",
    "img/patient.1cdc99c.svg",
    "img/pay-card.8fb80cc.svg",
    "img/pos-terminal.e54d71e.png",
    "img/responsive.bfad449.svg",
    "img/stock.b6becdb.svg"
  ],
  "initial": [
    "20f0c0a.js",
    "7b54047.js",
    "bd417ce.js",
    "6456d68.js"
  ],
  "async": [
    "0091f0b.js",
    "0521cd7.js",
    "0655349.js",
    "08c86a0.js",
    "09eb257.js",
    "0ab9730.js",
    "0dccafc.js",
    "0e52890.js",
    "102ffbc.js",
    "11651d5.js",
    "11a7210.js",
    "126a84d.js",
    "14e9e8d.js",
    "1879fdc.js",
    "1c9f7ce.js",
    "1d35849.js",
    "1d676ef.js",
    "20fcf78.js",
    "26e0e1c.js",
    "28fb761.js",
    "2e83be0.js",
    "2e90e47.js",
    "2f875ce.js",
    "32780cc.js",
    "338d535.js",
    "33d0554.js",
    "372b076.js",
    "37bd4c7.js",
    "3867d75.js",
    "39b8c1c.js",
    "3d8a986.js",
    "3f95d30.js",
    "4106bfa.js",
    "42720ec.js",
    "4442a57.js",
    "44786c9.js",
    "458b9f1.js",
    "4b1e8a3.js",
    "4c30673.js",
    "4d79287.js",
    "4e9fdbc.js",
    "54d54e1.js",
    "57b46cd.js",
    "5b02a74.js",
    "5ca6e04.js",
    "5debb3b.js",
    "5f15256.js",
    "5ff4294.js",
    "64b37f0.js",
    "66ee803.js",
    "6b6657d.js",
    "6c22cff.js",
    "6e8eb97.js",
    "7039dd4.js",
    "7132b24.js",
    "748dbac.js",
    "7557e2f.js",
    "75c7c22.js",
    "7f5a696.js",
    "822fb99.js",
    "8303e45.js",
    "837a01e.js",
    "864d5e0.js",
    "87ea06f.js",
    "8bc2018.js",
    "8cec888.js",
    "927b8f7.js",
    "946a562.js",
    "97f557a.js",
    "99a3003.js",
    "9b309b2.js",
    "9e92977.js",
    "a0fa3ac.js",
    "a21c123.js",
    "a6cb12b.js",
    "a777ec7.js",
    "b0e4ff8.js",
    "b404adc.js",
    "b512243.js",
    "b796d96.js",
    "b88c4ab.js",
    "bb2272a.js",
    "bcd9d9a.js",
    "bd13174.js",
    "be25047.js",
    "c45aa79.js",
    "c88a534.js",
    "cd1d049.js",
    "cd40c37.js",
    "d26d2f8.js",
    "d9a21fe.js",
    "dd13d0a.js",
    "de07aa1.js",
    "de25305.js",
    "decbd27.js",
    "df9264f.js",
    "dfad095.js",
    "e04c5ef.js",
    "e23cb26.js",
    "e47888f.js",
    "e8825c2.js",
    "ec237bc.js",
    "edff888.js",
    "f106e75.js",
    "f19ab22.js",
    "f49c04d.js",
    "f4d1f31.js",
    "fbb668d.js",
    "fdfbde4.js"
  ],
  "modules": {
    "10258052": [
      111
    ],
    "18037264": [
      90
    ],
    "19132244": [
      4
    ],
    "19589675": [
      90
    ],
    "21396522": [
      62
    ],
    "24689407": [
      62
    ],
    "25736990": [
      51,
      127,
      121,
      116,
      117,
      118,
      120,
      119
    ],
    "28545096": [
      62
    ],
    "34925769": [
      90
    ],
    "37602894": [
      88
    ],
    "43840079": [
      90
    ],
    "45685390": [
      90
    ],
    "45768185": [
      62
    ],
    "46118868": [
      62
    ],
    "46348864": [
      91
    ],
    "63416224": [
      76,
      22
    ],
    "64296727": [
      16,
      22,
      10
    ],
    "68226748": [
      62
    ],
    "73367258": [
      90
    ],
    "73839736": [
      62
    ],
    "76901674": [
      62
    ],
    "92040300": [
      62
    ],
    "96940652": [
      62
    ],
    "99748060": [
      17
    ],
    "2dae1aed": [
      90
    ],
    "70325df8": [
      62
    ],
    "652b46fa": [
      62
    ],
    "3f43f782": [
      51,
      127,
      121,
      116,
      117,
      118,
      120,
      119
    ],
    "853c63d4": [
      62
    ],
    "2f79b3aa": [
      90
    ],
    "2a53171f": [
      62
    ],
    "524efdbe": [
      62
    ],
    "6ce14d1c": [
      62
    ],
    "3514f006": [
      62
    ],
    "7e97d3a1": [
      62
    ],
    "9bd45a4a": [
      90
    ],
    "d39c4960": [
      62
    ],
    "30280a6b": [
      62
    ],
    "2feb2f7e": [
      90
    ],
    "bd9f158e": [
      90
    ],
    "c4d978e8": [
      90
    ],
    "51daa6dc": [
      90
    ],
    "e8230034": [
      62
    ],
    "44e4feee": [
      62
    ],
    "299f8083": [
      62
    ],
    "9e4c3ed6": [
      62
    ],
    "d2f91424": [
      62
    ],
    "d6bd7776": [
      62
    ],
    "607250fc": [
      90
    ],
    "36fc323e": [
      62
    ],
    "343bdc78": [
      62
    ],
    "1860f37f": [
      62
    ],
    "04ce5fd6": [
      62
    ],
    "0909cdb0": [
      62
    ],
    "28456cd0": [
      62
    ],
    "0125da40": [
      62
    ],
    "efb318da": [
      62
    ],
    "737f73ae": [
      62
    ],
    "364cc17a": [
      62
    ],
    "efc8e4e0": [
      90
    ],
    "6523d7fa": [
      62
    ],
    "e3be85f0": [
      62
    ],
    "019d4946": [
      62
    ],
    "731bfe92": [
      62
    ],
    "e04c1dd0": [
      62
    ],
    "b32cf36c": [
      62
    ],
    "8142c6d0": [
      62
    ],
    "f15e2156": [
      90
    ],
    "0c1297e8": [
      90
    ],
    "e3865d38": [
      62
    ],
    "4ac969dc": [
      62
    ],
    "69692b71": [
      62
    ],
    "70ce1299": [
      62
    ],
    "0834c7c2": [
      62
    ],
    "285921fe": [
      62
    ],
    "e0c3fc8e": [
      62
    ],
    "b72d7232": [
      62
    ],
    "a99be7d6": [
      62
    ],
    "6b99b27b": [
      90
    ],
    "4e891989": [
      90
    ],
    "7b5abb0b": [
      90
    ],
    "c84c0652": [
      90
    ],
    "00f51987": [
      90
    ],
    "32aead8e": [
      90
    ],
    "346d062c": [
      90
    ],
    "6f5a68ab": [
      90
    ],
    "4e1f5f48": [
      62
    ],
    "4438103c": [
      62
    ],
    "20ae1098": [
      62
    ],
    "eb7005be": [
      62
    ],
    "5338466a": [
      62
    ],
    "e99140ea": [
      51,
      127,
      121,
      116,
      117,
      118,
      120,
      119
    ],
    "59a1908c": [
      62
    ],
    "dc8303ea": [
      62
    ],
    "b5eef6b2": [
      62
    ],
    "e19ffd6a": [
      90
    ],
    "e351dd06": [
      62
    ],
    "15f15c80": [
      62
    ],
    "71dd62aa": [
      62
    ],
    "a5c324cc": [
      62
    ],
    "4fc47f9c": [
      62
    ],
    "0afc0b7e": [
      90
    ],
    "6051339c": [
      62
    ],
    "315f937d": [
      62
    ],
    "3b8e7273": [
      90
    ],
    "1ea43b24": [
      62
    ],
    "027eadd3": [
      62
    ],
    "159e5679": [
      62
    ],
    "6808cdaa": [
      62
    ],
    "2a97510f": [
      90
    ],
    "c4fa90e2": [
      90
    ],
    "33696f7a": [
      62
    ],
    "296ab3a2": [
      62
    ],
    "45df3a64": [
      62
    ],
    "620f89f0": [
      62
    ],
    "fb5e9cc8": [
      62
    ],
    "5ef9f680": [
      62
    ],
    "3492e14e": [
      90
    ],
    "1f982922": [
      90
    ],
    "3b4d9c19": [
      90
    ],
    "2da63529": [
      90
    ],
    "69b63df6": [
      62
    ],
    "36e036a4": [
      90
    ],
    "739eb32a": [
      62
    ],
    "3534d19e": [
      62
    ],
    "4df3b872": [
      62
    ],
    "0ce3f586": [
      90
    ],
    "469e45cf": [
      90
    ],
    "e6361cb2": [
      90
    ],
    "08e955c6": [
      90
    ],
    "3458626f": [
      90
    ],
    "652e90be": [
      62
    ],
    "4b931f5c": [
      62
    ],
    "7121c232": [
      62
    ],
    "5fe4c88b": [
      62
    ],
    "c54b1a12": [
      62
    ],
    "53791cd8": [
      62
    ],
    "76e0ad26": [
      62
    ],
    "0874adae": [
      90
    ],
    "55ed3049": [
      62
    ],
    "3c116d08": [
      62
    ],
    "a892e23a": [
      90
    ],
    "1a67dfc1": [
      51,
      127,
      121,
      116,
      117,
      118,
      120,
      119
    ],
    "6cd215b2": [
      51,
      127,
      121,
      116,
      117,
      118,
      120,
      119
    ],
    "995f50f0": [
      51,
      127,
      121,
      116,
      117,
      118,
      120,
      119
    ],
    "58d054ed": [
      51,
      127,
      121,
      116,
      117,
      118,
      120,
      119
    ],
    "065beef7": [
      51,
      127,
      121,
      116,
      117,
      118,
      120,
      119
    ],
    "58890b32": [
      51,
      127,
      121,
      116,
      117,
      118,
      120,
      119
    ],
    "7a0ce152": [
      51,
      127,
      121,
      116,
      117,
      118,
      120,
      119
    ],
    "a1ce27f2": [
      51,
      127,
      121,
      116,
      117,
      118,
      120,
      119
    ],
    "725ba572": [
      51,
      127,
      121,
      116,
      117,
      118,
      120,
      119
    ],
    "40b5131f": [
      51,
      127,
      121,
      116,
      117,
      118,
      120,
      119
    ],
    "1520acc6": [
      51,
      127,
      121,
      116,
      117,
      118,
      120,
      119
    ],
    "1946edbb": [
      51,
      127,
      121,
      116,
      117,
      118,
      120,
      119
    ],
    "fb36a0b6": [
      51,
      127,
      121,
      116,
      117,
      118,
      120,
      119
    ],
    "13b0e012": [
      51,
      127,
      121,
      116,
      117,
      118,
      120,
      119
    ],
    "c6cc18b6": [
      51,
      127,
      121,
      116,
      117,
      118,
      120,
      119
    ],
    "5e39d7f3": [
      51,
      127,
      121,
      116,
      117,
      118,
      120,
      119
    ],
    "2da71462": [
      51,
      127,
      121,
      116,
      117,
      118,
      120,
      119
    ],
    "e3490fc0": [
      51,
      127,
      121,
      116,
      117,
      118,
      120,
      119
    ],
    "6c8f9700": [
      51,
      127,
      121,
      116,
      117,
      118,
      120,
      119
    ],
    "3393dd58": [
      51,
      127,
      121,
      116,
      117,
      118,
      120,
      119
    ],
    "5fa69534": [
      51,
      127,
      121,
      116,
      117,
      118,
      120,
      119
    ],
    "58ccce0a": [
      51,
      127,
      121,
      116,
      117,
      118,
      120,
      119
    ],
    "429c4c64": [
      51,
      127,
      121,
      116,
      117,
      118,
      120,
      119
    ],
    "36aede79": [
      51,
      127,
      121,
      116,
      117,
      118,
      120,
      119
    ],
    "c75ec2e2": [
      51,
      127,
      121,
      116,
      117,
      118,
      120,
      119
    ],
    "289ce562": [
      51,
      127,
      121,
      116,
      117,
      118,
      120,
      119
    ],
    "7c829f96": [
      51,
      127,
      121,
      116,
      117,
      118,
      120,
      119
    ],
    "32652e5c": [
      51,
      127,
      121,
      116,
      117,
      118,
      120,
      119
    ],
    "276d4778": [
      51,
      127,
      121,
      116,
      117,
      118,
      120,
      119
    ],
    "1e614b16": [
      51,
      127,
      121,
      116,
      117,
      118,
      120,
      119
    ],
    "4f5c311d": [
      51,
      127,
      121,
      116,
      117,
      118,
      120,
      119
    ],
    "1191dc27": [
      51,
      127,
      121,
      116,
      117,
      118,
      120,
      119
    ],
    "51cf99b0": [
      51,
      127,
      121,
      116,
      117,
      118,
      120,
      119
    ],
    "70f55abe": [
      51,
      127,
      121,
      116,
      117,
      118,
      120,
      119
    ],
    "7badfdfa": [
      51,
      127,
      121,
      116,
      117,
      118,
      120,
      119
    ],
    "6bc60274": [
      51,
      127,
      121,
      116,
      117,
      118,
      120,
      119
    ],
    "7310ee2d": [
      51,
      127,
      121,
      116,
      117,
      118,
      120,
      119
    ],
    "78df350e": [
      51,
      127,
      121,
      116,
      117,
      118,
      120,
      119
    ],
    "74407a39": [
      51,
      127,
      121,
      116,
      117,
      118,
      120,
      119
    ],
    "17d14859": [
      51,
      127,
      121,
      116,
      117,
      118,
      120,
      119
    ],
    "570fba2a": [
      51,
      127,
      121,
      116,
      117,
      118,
      120,
      119
    ],
    "57be7528": [
      51,
      127,
      121,
      116,
      117,
      118,
      120,
      119
    ],
    "6b8f08dd": [
      51,
      127,
      121,
      116,
      117,
      118,
      120,
      119
    ],
    "54cc103f": [
      51,
      127,
      121,
      116,
      117,
      118,
      120,
      119
    ],
    "0d620471": [
      51,
      127,
      121,
      116,
      117,
      118,
      120,
      119
    ],
    "12c1c6ca": [
      51,
      127,
      121,
      116,
      117,
      118,
      120,
      119
    ],
    "b877d672": [
      90
    ],
    "1167de54": [
      62
    ],
    "7ad64858": [
      90
    ],
    "312ffe79": [
      62
    ],
    "a4a9117c": [
      62
    ],
    "199a6d91": [
      62
    ],
    "1dc11a87": [
      62
    ],
    "46a94200": [
      90
    ],
    "4bf1c13c": [
      90
    ],
    "7148010d": [
      90
    ],
    "10fe3cd0": [
      90
    ],
    "2a175f1b": [
      62
    ],
    "51ae5005": [
      62
    ],
    "1470156c": [
      62
    ],
    "76bf54ba": [
      62
    ],
    "69c7d00a": [
      62
    ],
    "27c26744": [
      62
    ],
    "307203dd": [
      90
    ],
    "1aa831ee": [
      90
    ],
    "47295af2": [
      90
    ],
    "6e51f25a": [
      90
    ],
    "0d5a4109": [
      90
    ],
    "7e610164": [
      90
    ],
    "6fd13fa4": [
      90
    ],
    "9e727d3c": [
      90
    ],
    "19828ec6": [
      62
    ],
    "690ed8b6": [
      62
    ],
    "07dcc506": [
      62
    ],
    "cc3c952c": [
      62
    ],
    "9a3e1664": [
      62
    ],
    "65e62202": [
      62
    ],
    "cf611a56": [
      62
    ],
    "2a2c5712": [
      62
    ],
    "f2b2c90c": [
      62
    ],
    "392ec746": [
      62
    ],
    "0f9e75da": [
      62
    ],
    "7dc9abfd": [
      62
    ],
    "bbdad2b2": [
      90
    ],
    "6e135cc8": [
      90
    ],
    "e3111992": [
      90
    ],
    "5fab0434": [
      90
    ],
    "c4655462": [
      90
    ],
    "9cf0c82e": [
      90
    ],
    "6b450d87": [
      90
    ],
    "4664ac90": [
      90
    ],
    "f1b55af8": [
      90
    ],
    "44e5ad05": [
      90
    ],
    "101c57e1": [
      62
    ],
    "1186a52a": [
      90
    ],
    "16d90cce": [
      90
    ],
    "02d60723": [
      62
    ],
    "f2bb103e": [
      62
    ],
    "9d5714c0": [
      62
    ],
    "57df9c8a": [
      62
    ],
    "eb4feaf8": [
      62
    ],
    "5647c9cd": [
      62
    ],
    "24b284bf": [
      62
    ],
    "0335f86c": [
      62
    ],
    "be017940": [
      62
    ],
    "7f57dc3d": [
      62
    ],
    "24dd5194": [
      62
    ],
    "f42ca9ce": [
      62
    ],
    "7fbeb04a": [
      62
    ],
    "a6d67cc8": [
      62
    ],
    "a981553e": [
      62
    ],
    "61861aec": [
      90
    ],
    "740e41f2": [
      90
    ],
    "b6921e22": [
      90
    ],
    "9630de6e": [
      51,
      127,
      121,
      116,
      117,
      118,
      120,
      119
    ],
    "f2a40e74": [
      62
    ],
    "9c223eea": [
      90
    ],
    "31ad4f64": [
      90
    ],
    "59e800c2": [
      90
    ],
    "5fd833c3": [
      90
    ],
    "45c8170e": [
      90
    ],
    "3e670472": [
      90
    ],
    "074d32ac": [
      90
    ],
    "4a03c180": [
      90
    ],
    "81af2a98": [
      90
    ],
    "21357e6b": [
      90
    ],
    "0da6f49d": [
      90
    ],
    "9a934ede": [
      90
    ],
    "b7a2acd8": [
      90
    ],
    "9b5b5226": [
      90
    ],
    "d00b41e6": [
      90
    ],
    "45db6514": [
      90
    ],
    "504c1d38": [
      90
    ],
    "70572bea": [
      90
    ],
    "bb365616": [
      90
    ],
    "4dcce1d3": [
      90
    ],
    "a78e1822": [
      90
    ],
    "e2d74cde": [
      62
    ],
    "839e1ad6": [
      90
    ],
    "4916fefc": [
      90
    ],
    "4b67de3f": [
      62
    ],
    "313ae1cf": [
      90
    ],
    "f2816048": [
      62
    ],
    "bfa8b386": [
      62
    ],
    "0e76add8": [
      62
    ],
    "67d975c9": [
      62
    ],
    "07f290d9": [
      62
    ],
    "e0b9c074": [
      62
    ],
    "8b49a528": [
      62
    ],
    "689324da": [
      62
    ],
    "8fbf5dfc": [
      62
    ],
    "bd8a986a": [
      62
    ],
    "f717f644": [
      62
    ],
    "ee422608": [
      62
    ],
    "7164f0e8": [
      62
    ],
    "495c1fc8": [
      62
    ],
    "617f46d2": [
      62
    ],
    "38ef0a12": [
      62
    ],
    "7ad14b26": [
      62
    ],
    "7d5c99e6": [
      62
    ],
    "5138a3f9": [
      62
    ],
    "60c152bf": [
      62
    ],
    "7c043974": [
      62
    ],
    "06b1d564": [
      90
    ],
    "67930dbe": [
      62
    ],
    "2545d33e": [
      90
    ],
    "755bd300": [
      62
    ],
    "4eb9cfb2": [
      62
    ],
    "18a1f08e": [
      62
    ],
    "15cc14dd": [
      90
    ],
    "90ac7352": [
      90
    ],
    "2f58749c": [
      90
    ],
    "c5c5d3c2": [
      90
    ],
    "d0cf6f06": [
      90
    ],
    "2cf82e76": [
      90
    ],
    "06a2cc8f": [
      90
    ],
    "d5cd071e": [
      90
    ],
    "2b890e99": [
      90
    ],
    "e054512a": [
      62
    ],
    "3ce6e5a4": [
      62
    ],
    "125ad76f": [
      90
    ],
    "717b92a2": [
      90
    ],
    "f055a6b2": [
      90
    ],
    "fd89f570": [
      90
    ],
    "5cb363c5": [
      51,
      127,
      121,
      116,
      117,
      118,
      120,
      119
    ],
    "4e205e33": [
      62
    ],
    "709b5ee2": [
      62
    ],
    "e79ce7bc": [
      62
    ],
    "4dde46ff": [
      62
    ],
    "a8850e2e": [
      90
    ],
    "bacccf1c": [
      62
    ],
    "1c611072": [
      62
    ],
    "7628c387": [
      62
    ],
    "3c7e6b97": [
      62
    ],
    "13e14379": [
      51,
      127,
      121,
      116,
      117,
      118,
      120,
      119
    ],
    "596eb67f": [
      51,
      127,
      121,
      116,
      117,
      118,
      120,
      119
    ],
    "2419c938": [
      51,
      127,
      121,
      116,
      117,
      118,
      120,
      119
    ],
    "37f2c4c3": [
      51,
      127,
      121,
      116,
      117,
      118,
      120,
      119
    ],
    "115a95c0": [
      51,
      127,
      121,
      116,
      117,
      118,
      120,
      119
    ],
    "18090a3a": [
      62
    ],
    "357648f4": [
      62
    ],
    "f4d49642": [
      62
    ],
    "485d94fc": [
      62
    ],
    "28653b2e": [
      62
    ],
    "d0e5e9a4": [
      62
    ],
    "ddc74f8a": [
      62
    ],
    "bf9c743e": [
      62
    ],
    "3c540900": [
      62
    ],
    "bceccc60": [
      62
    ],
    "c1bbccac": [
      62
    ],
    "69e8e6dc": [
      62
    ],
    "e6a28dcc": [
      62
    ],
    "45f05378": [
      62
    ],
    "a1ca583e": [
      62
    ],
    "745aea8a": [
      62
    ],
    "47ce4f16": [
      62
    ],
    "0c58ff32": [
      62
    ],
    "1e4f6ad5": [
      62
    ],
    "f6b9df04": [
      62
    ],
    "349506e4": [
      62
    ],
    "3ca259af": [
      62
    ],
    "303f9b08": [
      62
    ],
    "28ba0f04": [
      90
    ],
    "67bc5be8": [
      62
    ],
    "94103a68": [
      62
    ],
    "13da58c8": [
      62
    ],
    "29ff6933": [
      62
    ],
    "e9a52f5c": [
      62
    ],
    "20001c00": [
      62
    ],
    "b23d74f4": [
      62
    ],
    "e6866bd0": [
      62
    ],
    "35b692ea": [
      62
    ],
    "4fde5ef6": [
      62
    ],
    "450ddb37": [
      62
    ],
    "2b4ca37c": [
      62
    ],
    "2425b068": [
      62
    ],
    "4df69905": [
      90
    ],
    "408b879c": [
      90
    ],
    "1b2d4d99": [
      90
    ],
    "5d2a5b8f": [
      90
    ],
    "6e9127b3": [
      90
    ],
    "2744ecc6": [
      90
    ],
    "34e23462": [
      90
    ],
    "7074adcf": [
      90
    ],
    "63394ea9": [
      90
    ],
    "2b0391be": [
      90
    ],
    "20336a36": [
      90
    ],
    "60aad08a": [
      51,
      127,
      121,
      116,
      117,
      118,
      120,
      119
    ],
    "22cc6b46": [
      51,
      127,
      121,
      116,
      117,
      118,
      120,
      119
    ],
    "02482f62": [
      51,
      127,
      121,
      116,
      117,
      118,
      120,
      119
    ],
    "9a9492ec": [
      51,
      127,
      121,
      116,
      117,
      118,
      120,
      119
    ],
    "0adcc61e": [
      51,
      127,
      121,
      116,
      117,
      118,
      120,
      119
    ],
    "38a7601d": [
      90
    ],
    "4063432f": [
      90
    ],
    "5751d503": [
      90
    ],
    "110ec9d2": [
      90
    ],
    "f04642ce": [
      62
    ],
    "e9a018e0": [
      90
    ],
    "f99e1924": [
      90
    ],
    "2aa0cf60": [
      51,
      127,
      121,
      116,
      117,
      118,
      120,
      119
    ],
    "b5990546": [
      62
    ],
    "93dc7302": [
      90
    ],
    "78c7bc1c": [
      90
    ],
    "662d8f42": [
      90
    ],
    "120ab9f0": [
      90
    ],
    "1f6dddd7": [
      51,
      127,
      121,
      116,
      117,
      118,
      120,
      119
    ],
    "565237d8": [
      51,
      127,
      121,
      116,
      117,
      118,
      120,
      119
    ],
    "1ec74f14": [
      51,
      127,
      121,
      116,
      117,
      118,
      120,
      119
    ],
    "fd6909f0": [
      90
    ],
    "7ecfad5a": [
      51,
      127,
      121,
      116,
      117,
      118,
      120,
      119
    ],
    "0ac5d2b5": [
      90
    ],
    "ac1bf492": [
      90
    ],
    "46f90434": [
      90
    ],
    "1ac50972": [
      62
    ],
    "29406ac0": [
      62
    ],
    "6eb7ec0e": [
      90
    ],
    "3be3d79a": [
      90
    ],
    "3a2ecea8": [
      62
    ],
    "009de934": [
      62
    ],
    "1878872e": [
      62
    ],
    "7bba733d": [
      62
    ],
    "c69db0a6": [
      62
    ],
    "6a4bee1e": [
      62
    ],
    "4c0be3f8": [
      62
    ],
    "adf6bf52": [
      62
    ],
    "395b277c": [
      62
    ],
    "15d7e47a": [
      62
    ],
    "25beef1d": [
      62
    ],
    "46389a98": [
      62
    ],
    "128a64eb": [
      62
    ],
    "1736f0da": [
      62
    ],
    "11ea0c6a": [
      62
    ],
    "7213d908": [
      62
    ],
    "2c6b9a70": [
      62
    ],
    "0ca9c3f7": [
      62
    ],
    "21db287c": [
      62
    ],
    "514833ec": [
      62
    ],
    "70f0cc0e": [
      62
    ],
    "d337d8de": [
      62
    ],
    "5f4b00b3": [
      62
    ],
    "4770b168": [
      62
    ],
    "3dd96674": [
      62
    ],
    "6b61e9cd": [
      62
    ],
    "447cfeae": [
      62
    ],
    "e736cbb4": [
      62
    ],
    "1e3d226a": [
      62
    ],
    "33157e4e": [
      62
    ],
    "6181ed40": [
      62
    ],
    "1b232ea1": [
      62
    ],
    "4cf8f9e5": [
      62
    ],
    "ef8c133e": [
      62
    ],
    "741c12a0": [
      62
    ],
    "1b421cf2": [
      62
    ],
    "15a14e9d": [
      62
    ],
    "3571f91a": [
      62
    ],
    "6347a4a6": [
      62
    ],
    "f3a1a86e": [
      62
    ],
    "e1f8cab4": [
      62
    ],
    "7d5cd381": [
      62
    ],
    "499be741": [
      62
    ],
    "09435642": [
      62
    ],
    "4cc858fd": [
      62
    ],
    "4c5a4cc5": [
      62
    ],
    "1f433aea": [
      51,
      127,
      121,
      116,
      117,
      118,
      120,
      119
    ],
    "fa30497e": [
      51,
      127,
      121,
      116,
      117,
      118,
      120,
      119
    ],
    "34cd90c6": [
      90
    ],
    "6355d09e": [
      62
    ],
    "316d2b82": [
      62
    ],
    "839edc0e": [
      51,
      127,
      121,
      116,
      117,
      118,
      120,
      119
    ],
    "678e18ca": [
      51,
      127,
      121,
      116,
      117,
      118,
      120,
      119
    ],
    "46a1928d": [
      51,
      127,
      121,
      116,
      117,
      118,
      120,
      119
    ],
    "11a01318": [
      90
    ],
    "12afdcaa": [
      51,
      127,
      121,
      116,
      117,
      118,
      120,
      119
    ],
    "1730034a": [
      51,
      127,
      121,
      116,
      117,
      118,
      120,
      119
    ],
    "b8f3034c": [
      62
    ],
    "353d43f6": [
      62
    ],
    "66e35043": [
      62
    ],
    "7c8a5020": [
      62
    ],
    "1ca9202c": [
      62
    ],
    "079d0276": [
      62
    ],
    "2ea58b94": [
      62
    ],
    "bec96196": [
      62
    ],
    "4d45f8e1": [
      90
    ],
    "41c8c7b2": [
      62
    ],
    "225c6884": [
      90
    ],
    "1151ed37": [
      90
    ],
    "93dc27ee": [
      90
    ],
    "18c769ea": [
      90
    ],
    "020b2af7": [
      51,
      127,
      121,
      116,
      117,
      118,
      120,
      119
    ],
    "4f4d4d42": [
      62
    ],
    "038e9497": [
      62
    ],
    "673517bf": [
      62
    ],
    "33d09192": [
      51,
      127,
      121,
      116,
      117,
      118,
      120,
      119
    ],
    "1f4722f1": [
      51,
      127,
      121,
      116,
      117,
      118,
      120,
      119
    ],
    "5ac63416": [
      62
    ],
    "ecf5e56e": [
      62
    ],
    "4a7da4be": [
      62
    ],
    "4a842a0b": [
      62
    ],
    "fb8fb4dc": [
      62
    ],
    "2b823e79": [
      62
    ],
    "e7aef62c": [
      90
    ],
    "a5da12ba": [
      51,
      127,
      121,
      116,
      117,
      118,
      120,
      119
    ],
    "e5cf4aec": [
      90
    ],
    "1d6f5c20": [
      51,
      127,
      121,
      116,
      117,
      118,
      120,
      119
    ],
    "9adfd40a": [
      62
    ],
    "3ca7261a": [
      62
    ],
    "be8c3d68": [
      62
    ],
    "4938a9b6": [
      62
    ],
    "6b957e66": [
      62
    ],
    "5dfad0e1": [
      62
    ],
    "120fcb86": [
      62
    ],
    "4faa1c37": [
      62
    ],
    "e31e5a36": [
      62
    ],
    "c107ddb6": [
      62
    ],
    "0a0bff7a": [
      62
    ],
    "349a1c14": [
      62
    ],
    "6685129a": [
      62
    ],
    "4635549e": [
      62
    ],
    "2cafdf3e": [
      62
    ],
    "5cbdb086": [
      62
    ],
    "54686c32": [
      62
    ],
    "2005ad6d": [
      62
    ],
    "1e1ee884": [
      62
    ],
    "75ee3e34": [
      62
    ],
    "6b5141aa": [
      62
    ],
    "2aa25e94": [
      62
    ],
    "d6a9e548": [
      62
    ],
    "496d9cf4": [
      62
    ],
    "4281adf8": [
      62
    ],
    "55a63eea": [
      62
    ],
    "5f786974": [
      62
    ],
    "736744d8": [
      62
    ],
    "4f63e19e": [
      62
    ],
    "022e4b3a": [
      62
    ],
    "6b6d5eda": [
      62
    ],
    "fe761610": [
      62
    ],
    "0b4e502e": [
      62
    ],
    "44de8d2b": [
      51,
      127,
      121,
      116,
      117,
      118,
      120,
      119
    ],
    "6b07d289": [
      62
    ],
    "aa606266": [
      62
    ],
    "cb4e9eca": [
      62
    ],
    "1eb4a78e": [
      62
    ],
    "8e87e5d0": [
      90
    ],
    "cb3d8d44": [
      90
    ],
    "cf11da6a": [
      51,
      127,
      121,
      116,
      117,
      118,
      120,
      119
    ],
    "6d672bfe": [
      51,
      127,
      121,
      116,
      117,
      118,
      120,
      119
    ],
    "0cbadaa2": [
      51,
      127,
      121,
      116,
      117,
      118,
      120,
      119
    ],
    "cff4b250": [
      51,
      127,
      121,
      116,
      117,
      118,
      120,
      119
    ],
    "6a6940a9": [
      90
    ],
    "61029d00": [
      90
    ],
    "9070dc44": [
      51,
      127,
      121,
      116,
      117,
      118,
      120,
      119
    ],
    "558cff27": [
      51,
      127,
      121,
      116,
      117,
      118,
      120,
      119
    ],
    "3570dd8c": [
      51,
      127,
      121,
      116,
      117,
      118,
      120,
      119
    ],
    "ade3a490": [
      51,
      127,
      121,
      116,
      117,
      118,
      120,
      119
    ],
    "46d39b01": [
      51,
      127,
      121,
      116,
      117,
      118,
      120,
      119
    ],
    "f4d6c8bc": [
      51,
      127,
      121,
      116,
      117,
      118,
      120,
      119
    ],
    "4785d5b0": [
      51,
      127,
      121,
      116,
      117,
      118,
      120,
      119
    ],
    "9cb75880": [
      90
    ],
    "8bd5d6f4": [
      90
    ],
    "a8fc85aa": [
      62
    ],
    "7569dae3": [
      62
    ],
    "3912bee7": [
      62
    ],
    "7c915625": [
      62
    ],
    "28987ba5": [
      62
    ],
    "79680e23": [
      62
    ],
    "79d2e508": [
      62
    ],
    "66f9d2c9": [
      62
    ],
    "0e412b78": [
      90
    ],
    "4c18373e": [
      90
    ],
    "42276bdc": [
      62
    ],
    "3cb54cc6": [
      62
    ],
    "6c74cb38": [
      90
    ],
    "26e4517e": [
      90
    ],
    "6ab01fd8": [
      90
    ],
    "4c554c1e": [
      90
    ],
    "2d02af3c": [
      90
    ],
    "62b43bb0": [
      90
    ],
    "1a97151e": [
      62
    ],
    "19e00464": [
      90
    ],
    "001b3094": [
      90
    ],
    "6a400b9e": [
      90
    ],
    "c602e50a": [
      90
    ],
    "0ff2257e": [
      90
    ],
    "e1a2d2a6": [
      62
    ],
    "5754fb58": [
      90
    ],
    "417e8ad2": [
      90
    ],
    "afaa9fd0": [
      90
    ],
    "95943a44": [
      90
    ],
    "14906b2b": [
      90
    ],
    "1a940425": [
      90
    ],
    "a10a9850": [
      90
    ],
    "0a83139e": [
      90
    ],
    "c8ccc0c4": [
      90
    ],
    "53d42b98": [
      90
    ],
    "a3c98f10": [
      90
    ],
    "059ba884": [
      90
    ],
    "0e96c4d0": [
      90
    ],
    "05bfd05e": [
      90
    ],
    "17d1057b": [
      90
    ],
    "0ea3a978": [
      90
    ],
    "4e559fd4": [
      90
    ],
    "ad4400cc": [
      90
    ],
    "8c6414cc": [
      51,
      127,
      121,
      116,
      117,
      118,
      120,
      119
    ],
    "0aaa5750": [
      51,
      127,
      121,
      116,
      117,
      118,
      120,
      119
    ],
    "e7017e6e": [
      51,
      127,
      121,
      116,
      117,
      118,
      120,
      119
    ],
    "3eb1aa5a": [
      51,
      127,
      121,
      116,
      117,
      118,
      120,
      119
    ],
    "80552b24": [
      51,
      127,
      121,
      116,
      117,
      118,
      120,
      119
    ],
    "1eaa7cb8": [
      51,
      127,
      121,
      116,
      117,
      118,
      120,
      119
    ],
    "2fb675ba": [
      90
    ],
    "ea825500": [
      90
    ],
    "6bd52a66": [
      90
    ],
    "7244eba8": [
      90
    ],
    "325c26d8": [
      90
    ],
    "2668a5c4": [
      90
    ],
    "5766a790": [
      90
    ],
    "941c4f04": [
      90
    ],
    "3573ee9c": [
      90
    ],
    "24926d10": [
      90
    ],
    "2c22dfaa": [
      62
    ],
    "60b7065e": [
      90
    ],
    "4415f4b8": [
      90
    ],
    "3b1f8dfe": [
      90
    ],
    "de832010": [
      90
    ],
    "f06fed84": [
      90
    ],
    "331cfcf2": [
      90
    ],
    "0fc409b8": [
      90
    ],
    "6beb6334": [
      90
    ],
    "fc533ba8": [
      90
    ],
    "6a7299b8": [
      90
    ],
    "24e21ffe": [
      90
    ],
    "922e99d0": [
      90
    ],
    "05ffa65e": [
      90
    ],
    "10a98d18": [
      90
    ],
    "69cdd944": [
      90
    ],
    "24b47fdc": [
      62
    ],
    "7886e416": [
      62
    ],
    "3d285cb5": [
      62
    ],
    "c29b6264": [
      62
    ],
    "e8abc220": [
      62
    ],
    "7b084b1c": [
      90
    ],
    "60f1e590": [
      90
    ],
    "feeb5100": [
      90
    ],
    "65b19146": [
      90
    ],
    "cd9890a0": [
      90
    ],
    "d5b69110": [
      90
    ],
    "3788aa84": [
      90
    ],
    "3f083d8d": [
      90
    ],
    "77481dd3": [
      90
    ],
    "3d12a73c": [
      62
    ],
    "77bc495c": [
      90
    ],
    "1f2a3b18": [
      90
    ],
    "518f8e9c": [
      90
    ],
    "0f7818f8": [
      90
    ],
    "128c324c": [
      90
    ],
    "1f976512": [
      90
    ],
    "181ec7eb": [
      90
    ],
    "3fe7aeb1": [
      90
    ],
    "afc15dc8": [
      62
    ],
    "3100d8dc": [
      62
    ],
    "2c9f9a69": [
      51,
      127,
      121,
      116,
      117,
      118,
      120,
      119
    ],
    "7b8faa1a": [
      51,
      127,
      121,
      116,
      117,
      118,
      120,
      119
    ],
    "483c11f1": [
      51,
      127,
      121,
      116,
      117,
      118,
      120,
      119
    ],
    "2539dd0f": [
      51,
      127,
      121,
      116,
      117,
      118,
      120,
      119
    ],
    "bd4a7808": [
      51,
      127,
      121,
      116,
      117,
      118,
      120,
      119
    ],
    "23a55c9c": [
      51,
      127,
      121,
      116,
      117,
      118,
      120,
      119
    ],
    "ec5fff8c": [
      90
    ],
    "9cce3200": [
      90
    ],
    "02911250": [
      90
    ],
    "147ddfc4": [
      90
    ],
    "d324a5de": [
      51,
      127,
      121,
      116,
      117,
      118,
      120,
      119
    ],
    "05f031b7": [
      62
    ],
    "7c21341b": [
      62
    ],
    "2059e715": [
      62
    ],
    "326ed6dc": [
      62
    ],
    "38a4dd8a": [
      62
    ],
    "15bfe472": [
      62
    ],
    "d4622c5c": [
      62
    ],
    "4ca2b348": [
      62
    ],
    "ec1b79e2": [
      62
    ],
    "a31836ee": [
      62
    ],
    "2adfd294": [
      62
    ],
    "851194f8": [
      62
    ],
    "102ad5a6": [
      62
    ],
    "4157ffa5": [
      62
    ],
    "3b8ce617": [
      62
    ],
    "63acad64": [
      62
    ],
    "2421ab8a": [
      62
    ],
    "965f19a0": [
      90
    ],
    "e9247bd0": [
      90
    ],
    "4e2150b0": [
      62
    ],
    "8279a236": [
      51,
      127,
      121,
      116,
      117,
      118,
      120,
      119
    ],
    "56fe9ece": [
      51,
      127,
      121,
      116,
      117,
      118,
      120,
      119
    ],
    "5b5bc510": [
      51,
      127,
      121,
      116,
      117,
      118,
      120,
      119
    ],
    "0f443add": [
      51,
      127,
      121,
      116,
      117,
      118,
      120,
      119
    ],
    "081bf534": [
      51,
      127,
      121,
      116,
      117,
      118,
      120,
      119
    ],
    "2e2c2b22": [
      90
    ],
    "285da41e": [
      90
    ],
    "0c540b50": [
      37
    ],
    "210a62c2": [
      82
    ],
    "654909cf": [
      90
    ],
    "2daf2f77": [
      90
    ],
    "ca16b962": [
      90
    ],
    "cf4264dc": [
      90
    ],
    "5c88168b": [
      90
    ],
    "0a9fbc16": [
      90
    ],
    "20dd480f": [
      90
    ],
    "1f2b9ace": [
      90
    ],
    "5266fd9a": [
      90
    ],
    "40c477af": [
      90
    ],
    "f85ae31e": [
      90
    ],
    "138f758f": [
      90
    ],
    "09c0822f": [
      90
    ],
    "59e18e62": [
      90
    ],
    "05a2a347": [
      90
    ],
    "5856f3c0": [
      90
    ],
    "b8e7a4a0": [
      90
    ],
    "cf484042": [
      90
    ],
    "4aa8b176": [
      90
    ],
    "ecec8192": [
      90
    ],
    "1b9065f8": [
      90
    ],
    "1b27cef9": [
      90
    ],
    "5aef5ced": [
      90
    ],
    "408dc8f8": [
      90
    ],
    "1a135c5e": [
      90
    ],
    "e1a5c4c6": [
      90
    ],
    "015998ae": [
      90
    ],
    "1804b3a2": [
      90
    ],
    "05abfff7": [
      88
    ],
    "2cbc18b6": [
      88
    ],
    "92273e60": [
      88
    ],
    "9fa58f0c": [
      88
    ],
    "4eb017d6": [
      96
    ],
    "5abafb82": [
      18,
      96,
      60
    ],
    "b9188552": [
      18,
      96,
      60
    ],
    "6967e55e": [
      18,
      96,
      60
    ],
    "156e8c9b": [
      18,
      96,
      60
    ],
    "541abe1a": [
      18,
      96,
      60
    ],
    "1a7aefca": [
      112
    ],
    "1ca7156a": [
      112
    ],
    "40c77502": [
      112
    ],
    "2a6e1bae": [
      112
    ],
    "0de85e84": [
      112
    ],
    "326b41fc": [
      84,
      96
    ],
    "3d189464": [
      112
    ],
    "372a1d1f": [
      5
    ],
    "011c7728": [
      86,
      96
    ],
    "3b5d3d41": [
      22
    ],
    "d98e154e": [
      13,
      22
    ],
    "318ceaa9": [
      110,
      22
    ],
    "ea68ddba": [
      72,
      70,
      88
    ],
    "fd1113e2": [
      85
    ],
    "1e2edbba": [
      63,
      26,
      88
    ],
    "72b6d7a5": [
      27
    ],
    "6f3b95d3": [
      15
    ],
    "a9362596": [
      41,
      22
    ],
    "778a97cc": [
      24,
      22,
      88
    ],
    "f0b9787a": [
      6,
      22,
      88
    ],
    "7d13de39": [
      109,
      22,
      88
    ],
    "4c6f5989": [
      12,
      96
    ],
    "32e6a7b4": [
      101,
      96,
      12
    ],
    "0b382b90": [
      84,
      96
    ],
    "5133c8db": [
      33,
      22,
      88
    ],
    "006f0195": [
      29,
      22
    ],
    "727383fe": [
      76,
      22
    ],
    "02225460": [
      108,
      22,
      88,
      38
    ],
    "845107fe": [
      91
    ],
    "1037f44f": [
      2
    ],
    "a0ce78e2": [
      66,
      123
    ],
    "dbb6d986": [
      104,
      123
    ],
    "8ca70c14": [
      105,
      123
    ],
    "1b788bf2": [
      48,
      123
    ],
    "dc3adc6a": [
      55
    ],
    "61b71c48": [
      73
    ],
    "0e7d40ed": [
      81
    ],
    "63287d12": [
      12,
      96
    ],
    "a3f899d6": [
      12,
      96
    ],
    "c79ff80a": [
      12,
      96
    ],
    "cc3c215e": [
      12,
      96
    ],
    "00e0b482": [
      12,
      96
    ],
    "608514df": [
      106
    ],
    "f1929d84": [
      106
    ],
    "382388be": [
      106
    ],
    "65babf82": [
      106
    ],
    "4183227a": [
      106
    ],
    "402fc6c2": [
      83
    ],
    "18a11c9e": [
      83
    ],
    "1264b8fe": [
      83
    ],
    "5b990016": [
      83
    ],
    "1bc452ba": [
      83
    ],
    "3ec1b3bf": [
      10
    ],
    "17f2faee": [
      10
    ],
    "1ea1d9de": [
      10
    ],
    "5b874f32": [
      10
    ],
    "05a5a4cc": [
      10
    ],
    "46043c89": [
      96
    ],
    "f4e32d40": [
      96
    ],
    "e986de66": [
      112
    ],
    "2aad0652": [
      112
    ],
    "8c19ab38": [
      68,
      96,
      60,
      18,
      112,
      122,
      124,
      126,
      129,
      128,
      125
    ],
    "d79a934a": [
      68,
      96,
      60,
      18,
      112,
      122,
      124,
      126,
      129,
      128,
      125
    ],
    "7b8f46d3": [
      68,
      96,
      60,
      18,
      112,
      122,
      124,
      126,
      129,
      128,
      125
    ],
    "3f430878": [
      68,
      96,
      60,
      18,
      112,
      122,
      124,
      126,
      129,
      128,
      125
    ],
    "0193ddf2": [
      68,
      96,
      60,
      18,
      112,
      122,
      124,
      126,
      129,
      128,
      125
    ],
    "322e9b9a": [
      68,
      96,
      60,
      18,
      112,
      122,
      124,
      126,
      129,
      128,
      125
    ],
    "07e1ab80": [
      5
    ],
    "5cd7ecf6": [
      5
    ],
    "2379be8d": [
      86,
      96
    ],
    "40f33f43": [
      86,
      96
    ],
    "fadd06a4": [
      22
    ],
    "44cc4718": [
      22
    ],
    "d3940da4": [
      22
    ],
    "6789eb28": [
      22
    ],
    "d65af9f6": [
      22
    ],
    "24065f6a": [
      22
    ],
    "b3854d10": [
      22
    ],
    "77914b72": [
      22
    ],
    "abb34b20": [
      22
    ],
    "7b7a4c6a": [
      22
    ],
    "e0f488d0": [
      13,
      22
    ],
    "e42211bc": [
      13,
      22
    ],
    "5594e4ca": [
      110,
      22
    ],
    "730e6580": [
      110,
      22
    ],
    "b689623c": [
      72,
      70,
      88
    ],
    "3a53df6c": [
      72,
      70,
      88
    ],
    "c9319864": [
      85
    ],
    "30ffc458": [
      85
    ],
    "0ad84fe2": [
      63,
      26,
      88
    ],
    "bf1e3f28": [
      63,
      26,
      88
    ],
    "374b0a46": [
      27
    ],
    "42dd55fc": [
      27
    ],
    "3d2db752": [
      15
    ],
    "b8363b48": [
      15
    ],
    "79570eb4": [
      41,
      22
    ],
    "3fe38c84": [
      41,
      22
    ],
    "04d6996d": [
      24,
      22,
      88
    ],
    "58d661ba": [
      24,
      22,
      88
    ],
    "16f5c8a4": [
      6,
      22,
      88
    ],
    "b5b3444c": [
      6,
      22,
      88
    ],
    "0c66631a": [
      109,
      22,
      88
    ],
    "cad20f60": [
      109,
      22,
      88
    ],
    "3cc167ea": [
      12,
      96
    ],
    "a620c3c0": [
      12,
      96
    ],
    "970264b6": [
      101,
      96,
      12
    ],
    "1b35f8af": [
      101,
      96,
      12
    ],
    "1e6be459": [
      84,
      96
    ],
    "3be5650f": [
      84,
      96
    ],
    "43006b08": [
      33,
      22,
      88
    ],
    "a583ff9c": [
      33,
      22,
      88
    ],
    "633db9d8": [
      29,
      22
    ],
    "35184e1e": [
      29,
      22
    ],
    "97350c42": [
      76,
      22
    ],
    "5981a515": [
      76,
      22
    ],
    "18de938f": [
      108,
      22,
      88,
      38
    ],
    "a311b7ce": [
      108,
      22,
      88,
      38
    ],
    "1d69e2e2": [
      91
    ],
    "3167a418": [
      91
    ],
    "2a27b20e": [
      2
    ],
    "807f7ad0": [
      2
    ],
    "686613e4": [
      66,
      123
    ],
    "565511d0": [
      66,
      123
    ],
    "721621fc": [
      104,
      123
    ],
    "5b028886": [
      104,
      123
    ],
    "46f87b97": [
      105,
      123
    ],
    "15b6b14d": [
      105,
      123
    ],
    "f46aad5a": [
      48,
      123
    ],
    "c45b6cee": [
      48,
      123
    ],
    "383cedec": [
      55
    ],
    "d46acabc": [
      55
    ],
    "35c29e2e": [
      73
    ],
    "59bb289f": [
      73
    ],
    "7d7346a8": [
      81
    ],
    "24d57d94": [
      81
    ],
    "073a3b88": [
      82
    ],
    "7a11b414": [
      82
    ],
    "2a3a525b": [
      82
    ],
    "6bb3041e": [
      82
    ],
    "d8f22162": [
      82
    ],
    "166b04b9": [
      82
    ],
    "1770a3d0": [
      82
    ],
    "7121e5b1": [
      82
    ],
    "18dd7e0b": [
      82
    ],
    "b63635fa": [
      82
    ],
    "1182f1d2": [
      82
    ],
    "1c687a22": [
      82
    ],
    "75b768a8": [
      82
    ],
    "45e8c0f3": [
      38
    ],
    "1a73ac99": [
      38
    ],
    "f4121d8c": [
      38
    ],
    "64adc1d5": [
      38
    ],
    "3d9c33fe": [
      38
    ],
    "02ec1795": [
      50
    ],
    "48abb51e": [
      7
    ],
    "1edec810": [
      53
    ],
    "3b0d3f6e": [
      22
    ],
    "4d5039ad": [
      22
    ],
    "61441e08": [
      22
    ],
    "8ffc9976": [
      22
    ],
    "1a343c8a": [
      22
    ],
    "610c036f": [
      22
    ],
    "5f555e6e": [
      22
    ],
    "d4d7170c": [
      22
    ],
    "535624f0": [
      22
    ],
    "61a8bfa2": [
      22
    ],
    "8a54cc88": [
      22
    ],
    "fdf681ca": [
      22
    ],
    "ec786468": [
      22
    ],
    "f33cc166": [
      22
    ],
    "003525c3": [
      22
    ],
    "62d07f70": [
      22
    ],
    "b421a23a": [
      22
    ],
    "edbf1734": [
      22
    ],
    "18781f57": [
      22
    ],
    "382d3c36": [
      22
    ],
    "2ed95b9c": [
      68,
      96,
      60,
      18,
      112,
      122,
      124,
      126,
      129,
      128,
      125
    ],
    "03805a58": [
      68,
      96,
      60,
      18,
      112,
      122,
      124,
      126,
      129,
      128,
      125
    ],
    "99c98a4a": [
      68,
      96,
      60,
      18,
      112,
      122,
      124,
      126,
      129,
      128,
      125
    ],
    "995be6d8": [
      68,
      96,
      60,
      18,
      112,
      122,
      124,
      126,
      129,
      128,
      125
    ],
    "558ae09f": [
      68,
      96,
      60,
      18,
      112,
      122,
      124,
      126,
      129,
      128,
      125
    ],
    "b8ccbc9c": [
      61
    ],
    "6446d593": [
      61
    ],
    "5b34216a": [
      61
    ],
    "02d02852": [
      61
    ],
    "6c488107": [
      61
    ],
    "84947e12": [
      5
    ],
    "0156f98b": [
      5
    ],
    "ba597494": [
      5
    ],
    "61280ac7": [
      5
    ],
    "65b98c7a": [
      5
    ],
    "cf2b3f6c": [
      86,
      96
    ],
    "f073d3f0": [
      86,
      96
    ],
    "6c726dc3": [
      86,
      96
    ],
    "15f39978": [
      86,
      96
    ],
    "7670ae87": [
      86,
      96
    ],
    "924dc07c": [
      59,
      22
    ],
    "4e5f1f2e": [
      59,
      22
    ],
    "59f0318a": [
      59,
      22
    ],
    "dc19191c": [
      59,
      22
    ],
    "9cd98a12": [
      59,
      22
    ],
    "3ebaf578": [
      42,
      22
    ],
    "1871f345": [
      42,
      22
    ],
    "88f3500e": [
      42,
      22
    ],
    "5c064789": [
      42,
      22
    ],
    "cbdca896": [
      42,
      22
    ],
    "05c9bf8f": [
      36
    ],
    "f96c0c58": [
      36
    ],
    "6dc78be4": [
      36
    ],
    "331a4d18": [
      36
    ],
    "32218eca": [
      36
    ],
    "6062353a": [
      28,
      106
    ],
    "a8b90de4": [
      28,
      106
    ],
    "47430eba": [
      28,
      106
    ],
    "ee5eeb5c": [
      28,
      106
    ],
    "4fd7a576": [
      28,
      106
    ],
    "39f9ab48": [
      13,
      22
    ],
    "60b767d3": [
      13,
      22
    ],
    "5932a7e1": [
      13,
      22
    ],
    "0e7d1dd2": [
      13,
      22
    ],
    "43e5809d": [
      13,
      22
    ],
    "89cde05e": [
      32
    ],
    "3ca1e31e": [
      32
    ],
    "363ddc0c": [
      32
    ],
    "19cef462": [
      32
    ],
    "3ed272c8": [
      32
    ],
    "6c83d85e": [
      99,
      83
    ],
    "8ef36784": [
      99,
      83
    ],
    "bb294bc2": [
      99,
      83
    ],
    "94e242fc": [
      99,
      83
    ],
    "4123204a": [
      99,
      83
    ],
    "5ab021ea": [
      110,
      22
    ],
    "b5f49876": [
      110,
      22
    ],
    "514bc023": [
      110,
      22
    ],
    "1245d101": [
      110,
      22
    ],
    "5b4a00e7": [
      110,
      22
    ],
    "a09071b8": [
      72,
      70,
      88
    ],
    "71f1c70d": [
      72,
      70,
      88
    ],
    "0340f819": [
      72,
      70,
      88
    ],
    "01db1251": [
      72,
      70,
      88
    ],
    "0bd58ed5": [
      72,
      70,
      88
    ],
    "2649bab1": [
      85
    ],
    "0ca1e9bf": [
      85
    ],
    "9f2da5a8": [
      85
    ],
    "c6e995fa": [
      85
    ],
    "8e047830": [
      85
    ],
    "348afa01": [
      93
    ],
    "1d6de9b5": [
      93
    ],
    "aac06048": [
      93
    ],
    "6b2776f9": [
      93
    ],
    "4b002ad0": [
      93
    ],
    "0faf39c8": [
      63,
      26,
      88
    ],
    "19cb3c45": [
      63,
      26,
      88
    ],
    "a531f416": [
      63,
      26,
      88
    ],
    "ac96f0ee": [
      63,
      26,
      88
    ],
    "9408c69e": [
      63,
      26,
      88
    ],
    "1ee2a10c": [
      27
    ],
    "1c8f5486": [
      27
    ],
    "43dba17e": [
      27
    ],
    "5b3070f9": [
      27
    ],
    "d4911bf6": [
      27
    ],
    "2b75175d": [
      75
    ],
    "1dee2a02": [
      75
    ],
    "5e35a800": [
      75
    ],
    "23dd057a": [
      75
    ],
    "c98e8488": [
      75
    ],
    "141c786d": [
      15
    ],
    "5ffeafcb": [
      15
    ],
    "258298f0": [
      15
    ],
    "2589fc0f": [
      15
    ],
    "6285aeac": [
      15
    ],
    "6f083757": [
      67,
      96,
      60,
      18,
      112
    ],
    "18d84084": [
      67,
      96,
      60,
      18,
      112
    ],
    "decbd174": [
      67,
      96,
      60,
      18,
      112
    ],
    "13f55c70": [
      67,
      96,
      60,
      18,
      112
    ],
    "cda2a3fc": [
      67,
      96,
      60,
      18,
      112
    ],
    "3b0baef8": [
      41,
      22
    ],
    "5097b292": [
      41,
      22
    ],
    "31fc44c5": [
      41,
      22
    ],
    "c5811a0a": [
      41,
      22
    ],
    "6eff5a81": [
      41,
      22
    ],
    "153a7248": [
      24,
      22,
      88
    ],
    "7da3af2c": [
      24,
      22,
      88
    ],
    "674af185": [
      24,
      22,
      88
    ],
    "324a6330": [
      24,
      22,
      88
    ],
    "5a199f6e": [
      24,
      22,
      88
    ],
    "23f8bea2": [
      6,
      22,
      88
    ],
    "345e21a2": [
      6,
      22,
      88
    ],
    "0a54cf2a": [
      6,
      22,
      88
    ],
    "de2a9d2a": [
      6,
      22,
      88
    ],
    "4b1cb42f": [
      6,
      22,
      88
    ],
    "41a42f3e": [
      109,
      22,
      88
    ],
    "1ca39572": [
      109,
      22,
      88
    ],
    "04b5938c": [
      109,
      22,
      88
    ],
    "c67010fa": [
      109,
      22,
      88
    ],
    "54fcaf50": [
      109,
      22,
      88
    ],
    "d545c4dc": [
      16,
      22,
      10
    ],
    "b8edcda0": [
      16,
      22,
      10
    ],
    "f4c3d92a": [
      16,
      22,
      10
    ],
    "31c52518": [
      16,
      22,
      10
    ],
    "d668ca3a": [
      101,
      96,
      12
    ],
    "d991d69c": [
      101,
      96,
      12
    ],
    "2eea073a": [
      101,
      96,
      12
    ],
    "58c260f6": [
      101,
      96,
      12
    ],
    "6bed1cf6": [
      101,
      96,
      12
    ],
    "600698ad": [
      33,
      22,
      88
    ],
    "2f331a91": [
      33,
      22,
      88
    ],
    "d1d95280": [
      33,
      22,
      88
    ],
    "cf2b8c66": [
      33,
      22,
      88
    ],
    "02bb9584": [
      33,
      22,
      88
    ],
    "67f56af2": [
      29,
      22
    ],
    "22fd2299": [
      29,
      22
    ],
    "18dc7816": [
      29,
      22
    ],
    "2eef2246": [
      29,
      22
    ],
    "55df8dd2": [
      29,
      22
    ],
    "2b661c5e": [
      76,
      22
    ],
    "9e9cde9c": [
      76,
      22
    ],
    "e06c23a2": [
      76,
      22
    ],
    "133b0df3": [
      76,
      22
    ],
    "581786dd": [
      97
    ],
    "14971e94": [
      97
    ],
    "ddb472e0": [
      97
    ],
    "3fee85f2": [
      97
    ],
    "48cb0954": [
      97
    ],
    "4c78067e": [
      108,
      22,
      88,
      38
    ],
    "b893d0f4": [
      108,
      22,
      88,
      38
    ],
    "605cd1ff": [
      108,
      22,
      88,
      38
    ],
    "339f62ca": [
      108,
      22,
      88,
      38
    ],
    "68f168bb": [
      108,
      22,
      88,
      38
    ],
    "394b38cd": [
      91
    ],
    "08cb6ab7": [
      91
    ],
    "535564a0": [
      91
    ],
    "0a6db61a": [
      91
    ],
    "88c6dcfc": [
      2
    ],
    "408037bd": [
      2
    ],
    "ed80190a": [
      2
    ],
    "5f2cf9fe": [
      2
    ],
    "dc56eb92": [
      2
    ],
    "8e9e7c9e": [
      11
    ],
    "97cad212": [
      11
    ],
    "7daff3a8": [
      11
    ],
    "dd70af8a": [
      11
    ],
    "6c86c630": [
      11
    ],
    "6929e950": [
      44
    ],
    "92a5d4e0": [
      44
    ],
    "444aa316": [
      44
    ],
    "7f222ccc": [
      44
    ],
    "304e218e": [
      44
    ],
    "ddf6fe42": [
      9
    ],
    "f235839a": [
      9
    ],
    "743f1ebe": [
      9
    ],
    "56c26912": [
      9
    ],
    "b7c18d0c": [
      9
    ],
    "6d82d4aa": [
      39
    ],
    "3223bfa2": [
      39
    ],
    "1ab8e4fc": [
      39
    ],
    "1e01fbde": [
      39
    ],
    "42eaa946": [
      39
    ],
    "60100ecd": [
      14,
      96,
      60,
      18,
      112
    ],
    "627cbe8d": [
      14,
      96,
      60,
      18,
      112
    ],
    "2ab5f6c0": [
      14,
      96,
      60,
      18,
      112
    ],
    "2fdbd7c9": [
      14,
      96,
      60,
      18,
      112
    ],
    "564d4364": [
      14,
      96,
      60,
      18,
      112
    ],
    "ba5eb30e": [
      66,
      123
    ],
    "0b8fdc22": [
      66,
      123
    ],
    "75edcf38": [
      66,
      123
    ],
    "90364b9a": [
      66,
      123
    ],
    "632e9bc0": [
      66,
      123
    ],
    "d66ec5d0": [
      104,
      123
    ],
    "2ce3593f": [
      104,
      123
    ],
    "b913f6b6": [
      104,
      123
    ],
    "327f2083": [
      104,
      123
    ],
    "5953c13e": [
      104,
      123
    ],
    "3d843f68": [
      105,
      123
    ],
    "df643764": [
      105,
      123
    ],
    "7dc49001": [
      105,
      123
    ],
    "0cf5f8ec": [
      105,
      123
    ],
    "2d266276": [
      105,
      123
    ],
    "53bb972a": [
      48,
      123
    ],
    "f99b2828": [
      48,
      123
    ],
    "7d160ac2": [
      48,
      123
    ],
    "7b1eac28": [
      48,
      123
    ],
    "c0acaef4": [
      48,
      123
    ],
    "52002a38": [
      25,
      22
    ],
    "53e3f196": [
      25,
      22
    ],
    "d9efb72e": [
      25,
      22
    ],
    "c2f9c31e": [
      25,
      22
    ],
    "c5f335a6": [
      25,
      22
    ],
    "63d5f3bd": [
      55
    ],
    "439778eb": [
      55
    ],
    "373cd4a0": [
      55
    ],
    "e45ce3b2": [
      55
    ],
    "c7f24f18": [
      55
    ],
    "76ecb21c": [
      74
    ],
    "34ec4a16": [
      74
    ],
    "2056f7ca": [
      74
    ],
    "2fc3f031": [
      74
    ],
    "7154ccdf": [
      74
    ],
    "5a1b82f2": [
      40
    ],
    "06b72b3f": [
      40
    ],
    "5a1543ca": [
      40
    ],
    "35ad5f7b": [
      40
    ],
    "7456fc42": [
      40
    ],
    "2641d0d0": [
      17
    ],
    "7ac93426": [
      17
    ],
    "9f635bd8": [
      17
    ],
    "00c308ae": [
      17
    ],
    "f0edd0e2": [
      52
    ],
    "70248c70": [
      52
    ],
    "20cfe20e": [
      52
    ],
    "77be0d0c": [
      52
    ],
    "ec55926c": [
      52
    ],
    "2fbddcb0": [
      56
    ],
    "c336a2ca": [
      56
    ],
    "50c6b7b6": [
      56
    ],
    "426e64d7": [
      56
    ],
    "3afc45e9": [
      56
    ],
    "57d24738": [
      114
    ],
    "10fd3b13": [
      114
    ],
    "10b6e2d6": [
      114
    ],
    "4d1b5b62": [
      114
    ],
    "01a2cf59": [
      114
    ],
    "f4f73982": [
      64
    ],
    "77dc95be": [
      64
    ],
    "e3aba724": [
      64
    ],
    "3151d25d": [
      64
    ],
    "2dcd319c": [
      64
    ],
    "6fc9d38e": [
      57
    ],
    "118a54fc": [
      57
    ],
    "b83442b8": [
      57
    ],
    "f8f5b780": [
      57
    ],
    "e2ce9140": [
      57
    ],
    "74e5077e": [
      21
    ],
    "1aed8e7d": [
      21
    ],
    "0c55f2ff": [
      21
    ],
    "611b5ec1": [
      21
    ],
    "421fcabb": [
      21
    ],
    "e71cf5b6": [
      111
    ],
    "062b8a54": [
      111
    ],
    "52a8cb3e": [
      111
    ],
    "96e104cc": [
      111
    ],
    "ad4dd922": [
      84,
      96
    ],
    "6370792c": [
      84,
      96
    ],
    "4667c384": [
      84,
      96
    ],
    "3b87e0a6": [
      84,
      96
    ],
    "4bc26b8d": [
      4
    ],
    "a03bcacc": [
      4
    ],
    "5f27691c": [
      73
    ],
    "510f3bc4": [
      73
    ],
    "4cb3154c": [
      73
    ],
    "6bba2782": [
      100
    ],
    "726f255a": [
      100
    ],
    "749d3896": [
      100
    ],
    "5a4c0565": [
      81
    ],
    "3d83693f": [
      81
    ],
    "255886fa": [
      81
    ]
  },
  "assetsMapping": {
    "27927898": [
      "33d0554.js"
    ],
    "42531299": [
      "7f5a696.js"
    ],
    "a275515a": [
      "0091f0b.js"
    ],
    "7a55a123": [
      "0521cd7.js"
    ],
    "2c23d41e": [
      "0655349.js"
    ],
    "5c79aa16": [
      "08c86a0.js"
    ],
    "4d45bbfe": [
      "09eb257.js"
    ],
    "0e9293a0": [
      "0ab9730.js"
    ],
    "88d2abfc": [
      "0dccafc.js"
    ],
    "418c0430": [
      "0e52890.js"
    ],
    "e3c7e762": [
      "102ffbc.js"
    ],
    "361ef702": [
      "11651d5.js"
    ],
    "67c612f1": [
      "11a7210.js"
    ],
    "e4d6dea6": [
      "126a84d.js"
    ],
    "3911f628": [
      "14e9e8d.js"
    ],
    "d5199c04": [
      "1879fdc.js"
    ],
    "cfc123ba": [
      "1c9f7ce.js"
    ],
    "800dc976": [
      "1d35849.js"
    ],
    "4c573ef6": [
      "1d676ef.js"
    ],
    "6fca0322": [
      "20f0c0a.js"
    ],
    "81d5f244": [
      "20fcf78.js"
    ],
    "a6a72910": [
      "26e0e1c.js"
    ],
    "3e8984bd": [
      "28fb761.js"
    ],
    "03532558": [
      "2e83be0.js"
    ],
    "1d3c5de7": [
      "2e90e47.js"
    ],
    "57ff8ffa": [
      "2f875ce.js"
    ],
    "0f6008fd": [
      "32780cc.js"
    ],
    "72bbb5ab": [
      "338d535.js"
    ],
    "5f05bdd0": [
      "372b076.js"
    ],
    "e51ee236": [
      "37bd4c7.js"
    ],
    "7c7cf69e": [
      "3867d75.js"
    ],
    "a7b955bc": [
      "39b8c1c.js"
    ],
    "60fd7ecc": [
      "3d8a986.js"
    ],
    "136deace": [
      "3f95d30.js"
    ],
    "b906d886": [
      "4106bfa.js"
    ],
    "2539b060": [
      "42720ec.js"
    ],
    "bba68bf6": [
      "4442a57.js",
      "b0e4ff8.js"
    ],
    "041e9176": [
      "44786c9.js"
    ],
    "759c34ec": [
      "458b9f1.js"
    ],
    "1e6394fa": [
      "4b1e8a3.js"
    ],
    "53fd33ee": [
      "4c30673.js"
    ],
    "20a07ed5": [
      "4d79287.js"
    ],
    "78c66ae4": [
      "4e9fdbc.js"
    ],
    "85549b12": [
      "54d54e1.js"
    ],
    "8a919680": [
      "57b46cd.js"
    ],
    "71f6ce07": [
      "5b02a74.js"
    ],
    "29ca3dc8": [
      "5ca6e04.js"
    ],
    "160ff7ca": [
      "5debb3b.js"
    ],
    "6ed90953": [
      "5f15256.js"
    ],
    "56d44358": [
      "5ff4294.js"
    ],
    "1a3ae26b": [
      "6456d68.js"
    ],
    "5da4d39d": [
      "64b37f0.js"
    ],
    "5b6d7d2e": [
      "66ee803.js"
    ],
    "6b082e38": [
      "6b6657d.js"
    ],
    "7743ee48": [
      "6c22cff.js"
    ],
    "763c9ec8": [
      "6e8eb97.js"
    ],
    "1c90703f": [
      "7039dd4.js"
    ],
    "4457624c": [
      "7132b24.js"
    ],
    "9257ef5a": [
      "748dbac.js"
    ],
    "04d4ea47": [
      "7557e2f.js"
    ],
    "3303027a": [
      "75c7c22.js"
    ],
    "085a35c4": [
      "7b54047.js"
    ],
    "14ece624": [
      "822fb99.js"
    ],
    "400dd590": [
      "8303e45.js"
    ],
    "89e6e5ec": [
      "837a01e.js"
    ],
    "562f2fa8": [
      "864d5e0.js"
    ],
    "ce4a41de": [
      "87ea06f.js"
    ],
    "d74c0978": [
      "8bc2018.js"
    ],
    "089da459": [
      "8cec888.js"
    ],
    "35206bb8": [
      "927b8f7.js"
    ],
    "3b90adf5": [
      "946a562.js"
    ],
    "51bae372": [
      "97f557a.js"
    ],
    "2a130dde": [
      "99a3003.js"
    ],
    "1450c8ee": [
      "9b309b2.js"
    ],
    "1b06a4bd": [
      "9e92977.js"
    ],
    "4c5a625e": [
      "a0fa3ac.js"
    ],
    "3262d78c": [
      "a21c123.js"
    ],
    "2d56b7ba": [
      "a6cb12b.js"
    ],
    "48c4692d": [
      "a777ec7.js"
    ],
    "3ccc47e0": [
      "b404adc.js"
    ],
    "527d43e4": [
      "b512243.js"
    ],
    "7dc71ffc": [
      "b796d96.js"
    ],
    "1bcd5f2e": [
      "b88c4ab.js"
    ],
    "1e9d4158": [
      "bb2272a.js"
    ],
    "d60deb70": [
      "bcd9d9a.js"
    ],
    "02807acc": [
      "bd13174.js"
    ],
    "7ea24c87": [
      "bd417ce.js"
    ],
    "053837ac": [
      "be25047.js"
    ],
    "818ff2b6": [
      "c45aa79.js"
    ],
    "40f05e52": [
      "c88a534.js"
    ],
    "416b4bdc": [
      "cd1d049.js"
    ],
    "1e4d2248": [
      "cd40c37.js"
    ],
    "5ed4b1ba": [
      "d26d2f8.js"
    ],
    "a4b3a808": [
      "d9a21fe.js"
    ],
    "0c5c5f75": [
      "dd13d0a.js"
    ],
    "5722326f": [
      "de07aa1.js"
    ],
    "e81092fe": [
      "de25305.js"
    ],
    "25d1ff74": [
      "decbd27.js"
    ],
    "970d5dda": [
      "df9264f.js"
    ],
    "d284adac": [
      "dfad095.js"
    ],
    "da9db62e": [
      "e04c5ef.js"
    ],
    "290f6deb": [
      "e23cb26.js"
    ],
    "be256bc4": [
      "e47888f.js"
    ],
    "d392df28": [
      "e8825c2.js"
    ],
    "9e8aab62": [
      "ec237bc.js"
    ],
    "00f30340": [
      "edff888.js"
    ],
    "487e3bee": [
      "f106e75.js"
    ],
    "4c546258": [
      "f19ab22.js"
    ],
    "210b982c": [
      "f49c04d.js"
    ],
    "ccb0a61e": [
      "f4d1f31.js"
    ],
    "1ab4feed": [
      "fbb668d.js"
    ],
    "1c6c925d": [
      "fdfbde4.js"
    ]
  }
}